infernum/__init__.py
infernum/arch.py
infernum/const.py
infernum/core.py
infernum/exceptions.py
infernum/hooks.py
infernum/log.py
infernum/memory.py
infernum/structs.py
infernum/utils.py
infernum-0.1.1.dist-info/LICENSE
infernum-0.1.1.dist-info/METADATA
infernum-0.1.1.dist-info/WHEEL
infernum-0.1.1.dist-info/top_level.txt
infernum-0.1.1.dist-info/RECORD
