Metadata-Version: 2.1
Name: infernum
Version: 0.1.1
Summary: A lightweight Android native library emulation framework for executing the encryption algorithm.
Author: Sh4w
Author-email: sh4w0911@gmail.com
Classifier: License :: OSI Approved :: MIT License
Classifier: Operating System :: OS Independent
Classifier: Programming Language :: Python :: 3 :: Only
Classifier: Programming Language :: Python :: 3.7
Classifier: Programming Language :: Python :: 3.8
Classifier: Programming Language :: Python :: 3.9
Classifier: Programming Language :: Python :: 3.10
Classifier: Programming Language :: Python :: 3.11
Requires-Python: >=3.7
License-File: LICENSE
Requires-Dist: pyelftools (>=0.29)
Requires-Dist: unicorn (>=2.0.0)
Requires-Dist: capstone (>=4.0)
